MANIFEST.in
requirements.txt
setup.py
./stack/__init__.py
./stack/__main__.py
./stack/aiters.py
./stack/decorators.py
./stack/main.py
./stack/utils.py
./stack/wsh/__init__.py
./stack/wsh/__main__.py
./stack/wsh/client.py
./stack/wsh/main.py
./stack/wsh/server.py
./stack/wsh/test.py
./stack/wsh/wrappers.py
python_stack_cli.egg-info/PKG-INFO
python_stack_cli.egg-info/SOURCES.txt
python_stack_cli.egg-info/dependency_links.txt
python_stack_cli.egg-info/entry_points.txt
python_stack_cli.egg-info/requires.txt
python_stack_cli.egg-info/top_level.txt