Metadata-Version: 1.1
Name: python-stack-cli
Version: 0.2.15.5
Summary: `stack` is a Python version of [stack](http://docs.haskellstack.org/en/stable/README/),
Home-page: http://python-stack.readthedocs.io
Author: Ryan Kung
Author-email: ryankung@ieee.org
License: MIT
Platform: UNKNOWN
Classifier: Development Status :: 4 - Beta
Classifier: Environment :: Console
Classifier: Programming Language :: Python :: 3.5
Classifier: Operating System :: OS Independent
Classifier: Topic :: Software Development
Classifier: Topic :: Software Development :: Libraries :: Python Modules
